x_asyncio/__init__.py
x_asyncio-0.1.dist-info/METADATA
x_asyncio-0.1.dist-info/WHEEL
x_asyncio-0.1.dist-info/licenses/LICENSE
x_asyncio-0.1.dist-info/RECORD
