Metadata-Version: 2.4
Name: x-asyncio
Version: 0.1
Summary: A package to publish and receive messages
Project-URL: Homepage, https://github.com/shawn-peng/x-asyncio
Project-URL: Bug Tracker, https://github.com/shawn-peng/x-asyncio/issues
Author-email: Yisu Peng <yisupeng@gmail.com>
License-File: LICENSE
Classifier: License :: OSI Approved :: MIT License
Classifier: Operating System :: OS Independent
Classifier: Programming Language :: Python :: 3
Requires-Python: >=3.7
